odps/__init__.py
odps/core.py
odps/enums.py
odps/exceptions.py
odps/models.py
odps/protocols.py
odps/validation.py
odps/validators.py
odps_python-0.2.0.dist-info/licenses/LICENSE
odps_python-0.2.0.dist-info/METADATA
odps_python-0.2.0.dist-info/WHEEL
odps_python-0.2.0.dist-info/top_level.txt
odps_python-0.2.0.dist-info/RECORD
