Metadata-Version: 2.4
Name: odps-python
Version: 0.2.0
Summary: High-performance Python library for Open Data Product Specification (ODPS) v4.1 with ProductStrategy, AI integration, caching, validation, and international standards compliance
Author-email: Chris Howard <chris.howard@accenture.com>
License: Apache-2.0
Project-URL: Homepage, https://github.com/accenture/odps-python
Project-URL: Documentation, https://github.com/accenture/odps-python#readme
Project-URL: Repository, https://github.com/accenture/odps-python
Project-URL: Bug Tracker, https://github.com/accenture/odps-python/issues
Keywords: open-data,data-product,specification,odps,iso-standards,validation,rfc,e164,iso639,iso3166,iso4217,iso8601,performance,caching,protocols,type-safety
Classifier: Development Status :: 4 - Beta
Classifier: Intended Audience :: Developers
Classifier: Intended Audience :: Information Technology
Classifier: License :: OSI Approved :: Apache Software License
Classifier: Operating System :: OS Independent
Classifier: Programming Language :: Python :: 3
Classifier: Programming Language :: Python :: 3.8
Classifier: Programming Language :: Python :: 3.9
Classifier: Programming Language :: Python :: 3.10
Classifier: Programming Language :: Python :: 3.11
Classifier: Programming Language :: Python :: 3.12
Classifier: Topic :: Software Development :: Libraries :: Python Modules
Classifier: Topic :: Internet :: WWW/HTTP
Classifier: Topic :: Scientific/Engineering :: Information Analysis
Classifier: Topic :: Database
Requires-Python: >=3.8
License-File: LICENSE
Requires-Dist: PyYAML>=6.0.2
Requires-Dist: pycountry>=24.6.1
Requires-Dist: phonenumbers>=9.0.11
Provides-Extra: validation
Requires-Dist: pycountry>=24.6.1; extra == "validation"
Requires-Dist: phonenumbers>=9.0.11; extra == "validation"
Provides-Extra: dev
Requires-Dist: pytest>=6.0; extra == "dev"
Requires-Dist: pytest-cov>=3.0.0; extra == "dev"
Requires-Dist: black>=22.0; extra == "dev"
Requires-Dist: flake8>=4.0; extra == "dev"
Requires-Dist: mypy>=0.991; extra == "dev"
Requires-Dist: pycountry>=24.6.1; extra == "dev"
Requires-Dist: phonenumbers>=9.0.11; extra == "dev"
Requires-Dist: build>=0.8.0; extra == "dev"
Requires-Dist: twine>=4.0.0; extra == "dev"
Dynamic: license-file
